{
  "uniqueID" : "4dba3c24-3267-49ab-9d26-e42b24942b50",
  "floors" : [ {
    "uniqueID" : "41572329-c3d2-4b15-a9b3-1c3080af9fe5",
    "floor" : 1,
    "currentBuilding" : "4dba3c24-3267-49ab-9d26-e42b24942b50",
    "locationNodes" : [ {
      "uniqueID" : "bacd675b-169a-4812-8dc2-cde6121ac3ee",
      "heuristicCost" : 0.0,
      "location" : {
        "x" : 10.0,
        "y" : 10.0
      },
      "adjacentLocationNodes" : [ ],
      "destinations" : {
        "DEPARTMENT" : [ "Audiology" ]
      },
      "currentFloor" : "41572329-c3d2-4b15-a9b3-1c3080af9fe5",
      "buildingDestinations" : [ "Audiology" ]
    }, {
      "uniqueID" : "e53e4fa6-eca5-461d-a4d5-cec00600c6ef",
      "heuristicCost" : 0.0,
      "location" : {
        "x" : 10.0,
        "y" : 20.0
      },
      "adjacentLocationNodes" : [ ],
      "destinations" : {
        "DEPARTMENT" : [ "Cardiac Rehabilitation" ]
      },
      "currentFloor" : "41572329-c3d2-4b15-a9b3-1c3080af9fe5",
      "buildingDestinations" : [ "Cardiac Rehabilitation" ]
    }, {
      "uniqueID" : "9af59d1d-1fe9-4569-a095-8636cbb5dad2",
      "heuristicCost" : 0.0,
      "location" : {
        "x" : 10.0,
        "y" : 30.0
      },
      "adjacentLocationNodes" : [ ],
      "destinations" : {
        "DEPARTMENT" : [ "Center for Preoperative Evaluation" ]
      },
      "currentFloor" : "41572329-c3d2-4b15-a9b3-1c3080af9fe5",
      "buildingDestinations" : [ "Center for Preoperative Evaluation" ]
    }, {
      "uniqueID" : "abc6ee1f-8d58-4c85-acf7-9afd6ecef8af",
      "heuristicCost" : 0.0,
      "location" : {
        "x" : 10.0,
        "y" : 40.0
      },
      "adjacentLocationNodes" : [ ],
      "destinations" : {
        "DEPARTMENT" : [ "Emergency Room" ]
      },
      "currentFloor" : "41572329-c3d2-4b15-a9b3-1c3080af9fe5",
      "buildingDestinations" : [ "Emergency Room" ]
    }, {
      "uniqueID" : "1d46bd27-2e68-47b7-902a-58dbb578cfd9",
      "heuristicCost" : 0.0,
      "location" : {
        "x" : 10.0,
        "y" : 50.0
      },
      "adjacentLocationNodes" : [ ],
      "destinations" : {
        "DEPARTMENT" : [ "GI Endoscopy" ]
      },
      "currentFloor" : "41572329-c3d2-4b15-a9b3-1c3080af9fe5",
      "buildingDestinations" : [ "GI Endoscopy" ]
    }, {
      "uniqueID" : "5993a740-efe5-4e2d-b4f0-5858cc414e84",
      "heuristicCost" : 0.0,
      "location" : {
        "x" : 10.0,
        "y" : 60.0
      },
      "adjacentLocationNodes" : [ ],
      "destinations" : {
        "DEPARTMENT" : [ "Laboratory" ]
      },
      "currentFloor" : "41572329-c3d2-4b15-a9b3-1c3080af9fe5",
      "buildingDestinations" : [ "Laboratory" ]
    }, {
      "uniqueID" : "3316af77-a6b8-4241-8889-04628b5f344f",
      "heuristicCost" : 0.0,
      "location" : {
        "x" : 10.0,
        "y" : 70.0
      },
      "adjacentLocationNodes" : [ ],
      "destinations" : {
        "DEPARTMENT" : [ "Patient Financial Services" ]
      },
      "currentFloor" : "41572329-c3d2-4b15-a9b3-1c3080af9fe5",
      "buildingDestinations" : [ "Patient Financial Services" ]
    }, {
      "uniqueID" : "fb75b66e-d946-44e1-87ee-c69d620af5ee",
      "heuristicCost" : 0.0,
      "location" : {
        "x" : 10.0,
        "y" : 80.0
      },
      "adjacentLocationNodes" : [ ],
      "destinations" : {
        "DEPARTMENT" : [ "Radiology" ]
      },
      "currentFloor" : "41572329-c3d2-4b15-a9b3-1c3080af9fe5",
      "buildingDestinations" : [ "Radiology" ]
    }, {
      "uniqueID" : "89f85753-2d4c-46a8-9fe9-771aefd426b7",
      "heuristicCost" : 0.0,
      "location" : {
        "x" : 10.0,
        "y" : 90.0
      },
      "adjacentLocationNodes" : [ ],
      "destinations" : {
        "DEPARTMENT" : [ "Special Testing" ]
      },
      "currentFloor" : "41572329-c3d2-4b15-a9b3-1c3080af9fe5",
      "buildingDestinations" : [ "Special Testing" ]
    }, {
      "uniqueID" : "708f163c-0ba6-4c13-8df0-147b21abc11c",
      "heuristicCost" : 0.0,
      "location" : {
        "x" : 10.0,
        "y" : 100.0
      },
      "adjacentLocationNodes" : [ ],
      "destinations" : {
        "DEPARTMENT" : [ "Taiclet Family Center" ]
      },
      "currentFloor" : "41572329-c3d2-4b15-a9b3-1c3080af9fe5",
      "buildingDestinations" : [ "Taiclet Family Center" ]
    }, {
      "uniqueID" : "2f3bd5cf-92b2-4b6e-b311-b62a2c1fedc9",
      "heuristicCost" : 0.0,
      "location" : {
        "x" : 10.0,
        "y" : 110.0
      },
      "adjacentLocationNodes" : [ ],
      "destinations" : { },
      "currentFloor" : "41572329-c3d2-4b15-a9b3-1c3080af9fe5",
      "buildingDestinations" : [ ]
    }, {
      "uniqueID" : "5f922858-4b92-48c6-98fd-38ffd9e0cc2e",
      "heuristicCost" : 0.0,
      "location" : {
        "x" : 10.0,
        "y" : 120.0
      },
      "adjacentLocationNodes" : [ ],
      "destinations" : { },
      "currentFloor" : "41572329-c3d2-4b15-a9b3-1c3080af9fe5",
      "buildingDestinations" : [ ]
    }, {
      "uniqueID" : "5477c9db-7dc2-4d17-a24c-1fcf0a5acfb4",
      "heuristicCost" : 0.0,
      "location" : {
        "x" : 10.0,
        "y" : 130.0
      },
      "adjacentLocationNodes" : [ ],
      "destinations" : { },
      "currentFloor" : "41572329-c3d2-4b15-a9b3-1c3080af9fe5",
      "buildingDestinations" : [ ]
    }, {
      "uniqueID" : "44a538c8-e394-48f2-ab73-95a633d8d231",
      "heuristicCost" : 0.0,
      "location" : {
        "x" : 10.0,
        "y" : 140.0
      },
      "adjacentLocationNodes" : [ ],
      "destinations" : { },
      "currentFloor" : "41572329-c3d2-4b15-a9b3-1c3080af9fe5",
      "buildingDestinations" : [ ]
    }, {
      "uniqueID" : "1cafadaa-f103-4adb-a24c-768cba5c5b3b",
      "heuristicCost" : 0.0,
      "location" : {
        "x" : 10.0,
        "y" : 10.0
      },
      "adjacentLocationNodes" : [ ],
      "destinations" : {
        "DEPARTMENT" : [ "Audiology" ]
      },
      "currentFloor" : "41572329-c3d2-4b15-a9b3-1c3080af9fe5",
      "buildingDestinations" : [ "Audiology" ]
    }, {
      "uniqueID" : "eee3706c-45f7-40f8-bc87-344234fbc18b",
      "heuristicCost" : 0.0,
      "location" : {
        "x" : 10.0,
        "y" : 20.0
      },
      "adjacentLocationNodes" : [ ],
      "destinations" : {
        "DEPARTMENT" : [ "Cardiac Rehabilitation" ]
      },
      "currentFloor" : "41572329-c3d2-4b15-a9b3-1c3080af9fe5",
      "buildingDestinations" : [ "Cardiac Rehabilitation" ]
    }, {
      "uniqueID" : "5c343212-627c-4a3a-9d03-167d8927a313",
      "heuristicCost" : 0.0,
      "location" : {
        "x" : 10.0,
        "y" : 30.0
      },
      "adjacentLocationNodes" : [ ],
      "destinations" : {
        "DEPARTMENT" : [ "Center for Preoperative Evaluation" ]
      },
      "currentFloor" : "41572329-c3d2-4b15-a9b3-1c3080af9fe5",
      "buildingDestinations" : [ "Center for Preoperative Evaluation" ]
    }, {
      "uniqueID" : "9f60739f-c1f4-4d8c-a63d-289db7ce69e1",
      "heuristicCost" : 0.0,
      "location" : {
        "x" : 10.0,
        "y" : 40.0
      },
      "adjacentLocationNodes" : [ ],
      "destinations" : {
        "DEPARTMENT" : [ "Emergency Room" ]
      },
      "currentFloor" : "41572329-c3d2-4b15-a9b3-1c3080af9fe5",
      "buildingDestinations" : [ "Emergency Room" ]
    }, {
      "uniqueID" : "0322bf51-8790-4238-b407-36fb7ac3d6e6",
      "heuristicCost" : 0.0,
      "location" : {
        "x" : 10.0,
        "y" : 50.0
      },
      "adjacentLocationNodes" : [ ],
      "destinations" : {
        "DEPARTMENT" : [ "GI Endoscopy" ]
      },
      "currentFloor" : "41572329-c3d2-4b15-a9b3-1c3080af9fe5",
      "buildingDestinations" : [ "GI Endoscopy" ]
    }, {
      "uniqueID" : "50caf042-7990-400b-9eed-f0f345c4d313",
      "heuristicCost" : 0.0,
      "location" : {
        "x" : 10.0,
        "y" : 60.0
      },
      "adjacentLocationNodes" : [ ],
      "destinations" : {
        "DEPARTMENT" : [ "Laboratory" ]
      },
      "currentFloor" : "41572329-c3d2-4b15-a9b3-1c3080af9fe5",
      "buildingDestinations" : [ "Laboratory" ]
    }, {
      "uniqueID" : "9defd321-b0af-4fd1-9b52-c4e3273fafad",
      "heuristicCost" : 0.0,
      "location" : {
        "x" : 10.0,
        "y" : 70.0
      },
      "adjacentLocationNodes" : [ ],
      "destinations" : {
        "SERVICE" : [ "Patient Financial Services" ]
      },
      "currentFloor" : "41572329-c3d2-4b15-a9b3-1c3080af9fe5",
      "buildingDestinations" : [ "Patient Financial Services" ]
    }, {
      "uniqueID" : "bd90d82a-6992-4d81-a008-e760964b8050",
      "heuristicCost" : 0.0,
      "location" : {
        "x" : 10.0,
        "y" : 80.0
      },
      "adjacentLocationNodes" : [ ],
      "destinations" : {
        "DEPARTMENT" : [ "Radiology" ]
      },
      "currentFloor" : "41572329-c3d2-4b15-a9b3-1c3080af9fe5",
      "buildingDestinations" : [ "Radiology" ]
    }, {
      "uniqueID" : "3e4f4132-9384-4939-ba8b-d65de36f9d24",
      "heuristicCost" : 0.0,
      "location" : {
        "x" : 10.0,
        "y" : 90.0
      },
      "adjacentLocationNodes" : [ ],
      "destinations" : {
        "DEPARTMENT" : [ "Special Testing" ]
      },
      "currentFloor" : "41572329-c3d2-4b15-a9b3-1c3080af9fe5",
      "buildingDestinations" : [ "Special Testing" ]
    }, {
      "uniqueID" : "5a00a134-923b-43c7-842d-73eed9f775c2",
      "heuristicCost" : 0.0,
      "location" : {
        "x" : 10.0,
        "y" : 100.0
      },
      "adjacentLocationNodes" : [ ],
      "destinations" : {
        "DEPARTMENT" : [ "Taiclet Family Center" ]
      },
      "currentFloor" : "41572329-c3d2-4b15-a9b3-1c3080af9fe5",
      "buildingDestinations" : [ "Taiclet Family Center" ]
    }, {
      "uniqueID" : "b6005d00-4bf1-4fe4-8333-d30b10366dd4",
      "heuristicCost" : 0.0,
      "location" : {
        "x" : 10.0,
        "y" : 110.0
      },
      "adjacentLocationNodes" : [ ],
      "destinations" : { },
      "currentFloor" : "41572329-c3d2-4b15-a9b3-1c3080af9fe5",
      "buildingDestinations" : [ ]
    }, {
      "uniqueID" : "fa6365ce-aa3c-4fbd-ab8e-81a2515ffdae",
      "heuristicCost" : 0.0,
      "location" : {
        "x" : 10.0,
        "y" : 120.0
      },
      "adjacentLocationNodes" : [ ],
      "destinations" : { },
      "currentFloor" : "41572329-c3d2-4b15-a9b3-1c3080af9fe5",
      "buildingDestinations" : [ ]
    }, {
      "uniqueID" : "fc3e751c-f13a-40b5-b4c0-30c541cb6edc",
      "heuristicCost" : 0.0,
      "location" : {
        "x" : 10.0,
        "y" : 130.0
      },
      "adjacentLocationNodes" : [ ],
      "destinations" : { },
      "currentFloor" : "41572329-c3d2-4b15-a9b3-1c3080af9fe5",
      "buildingDestinations" : [ ]
    }, {
      "uniqueID" : "fa35dbe0-dd67-41c4-8eb2-2efae16a3d25",
      "heuristicCost" : 0.0,
      "location" : {
        "x" : 10.0,
        "y" : 140.0
      },
      "adjacentLocationNodes" : [ ],
      "destinations" : { },
      "currentFloor" : "41572329-c3d2-4b15-a9b3-1c3080af9fe5",
      "buildingDestinations" : [ ]
    } ],
    "imagePath" : "Floor1_Final.png"
  }, {
    "uniqueID" : "3021ba43-9ef0-4d9e-a68d-7918bd77b9ed",
    "floor" : 2,
    "currentBuilding" : "4dba3c24-3267-49ab-9d26-e42b24942b50",
    "locationNodes" : [ {
      "uniqueID" : "02132a9b-9d94-45b8-ac29-d815b0d4994a",
      "heuristicCost" : 0.0,
      "location" : {
        "x" : 20.0,
        "y" : 10.0
      },
      "adjacentLocationNodes" : [ ],
      "destinations" : {
        "PHYSICIAN" : [ "Corrales, Carleton Eduardo, MD", "Prince, Anthony, MD", "Roditi, Rachel, MD" ],
        "DEPARTMENT" : [ "Otolarngology" ]
      },
      "currentFloor" : "3021ba43-9ef0-4d9e-a68d-7918bd77b9ed",
      "buildingDestinations" : [ "Corrales, Carleton Eduardo, MD", "Prince, Anthony, MD", "Roditi, Rachel, MD", "Otolarngology" ]
    }, {
      "uniqueID" : "2d6a514c-c81f-4a19-b73d-510d850f3189",
      "heuristicCost" : 0.0,
      "location" : {
        "x" : 20.0,
        "y" : 20.0
      },
      "adjacentLocationNodes" : [ ],
      "destinations" : {
        "PHYSICIAN" : [ "Carty, Matthew, MD", "Caterson, Stephanie, MD", "Chun, Yoon Sun, MD", "Hajj, Micheline, RN", "Halvorson, Eric, MD", "Hergrueter, Charles, MD", "Ingram, Abbie, PA-C", "Lafleur, Emily, PA-C", "Lahair, Tracy, PA-C" ],
        "DEPARTMENT" : [ "Plastic Surgery" ]
      },
      "currentFloor" : "3021ba43-9ef0-4d9e-a68d-7918bd77b9ed",
      "buildingDestinations" : [ "Carty, Matthew, MD", "Caterson, Stephanie, MD", "Chun, Yoon Sun, MD", "Hajj, Micheline, RN", "Halvorson, Eric, MD", "Hergrueter, Charles, MD", "Ingram, Abbie, PA-C", "Lafleur, Emily, PA-C", "Lahair, Tracy, PA-C", "Plastic Surgery" ]
    }, {
      "uniqueID" : "88c5f8d5-e95f-4c02-92ac-c12e4ea02ea1",
      "heuristicCost" : 0.0,
      "location" : {
        "x" : 20.0,
        "y" : 40.0
      },
      "adjacentLocationNodes" : [ ],
      "destinations" : {
        "DEPARTMENT" : [ "Physical Therapy" ]
      },
      "currentFloor" : "3021ba43-9ef0-4d9e-a68d-7918bd77b9ed",
      "buildingDestinations" : [ "Physical Therapy" ]
    }, {
      "uniqueID" : "be4a70d1-eaca-4e16-9abf-a580e39456ac",
      "heuristicCost" : 0.0,
      "location" : {
        "x" : 20.0,
        "y" : 50.0
      },
      "adjacentLocationNodes" : [ ],
      "destinations" : {
        "DEPARTMENT" : [ "Psychology" ]
      },
      "currentFloor" : "3021ba43-9ef0-4d9e-a68d-7918bd77b9ed",
      "buildingDestinations" : [ "Psychology" ]
    }, {
      "uniqueID" : "477b23a8-dc55-4458-85db-10ec27b31b86",
      "heuristicCost" : 0.0,
      "location" : {
        "x" : 20.0,
        "y" : 10.0
      },
      "adjacentLocationNodes" : [ ],
      "destinations" : {
        "PHYSICIAN" : [ "Corrales, Carleton Eduardo, MD", "Prince, Anthony, MD", "Roditi, Rachel, MD" ],
        "DEPARTMENT" : [ "Otolarngology" ]
      },
      "currentFloor" : "3021ba43-9ef0-4d9e-a68d-7918bd77b9ed",
      "buildingDestinations" : [ "Corrales, Carleton Eduardo, MD", "Prince, Anthony, MD", "Roditi, Rachel, MD", "Otolarngology" ]
    }, {
      "uniqueID" : "fcf29e1b-af4d-4cfe-a541-041026de5403",
      "heuristicCost" : 0.0,
      "location" : {
        "x" : 20.0,
        "y" : 20.0
      },
      "adjacentLocationNodes" : [ ],
      "destinations" : {
        "PHYSICIAN" : [ "Carty, Matthew, MD", "Caterson, Stephanie, MD", "Chun, Yoon Sun, MD", "Hajj, Micheline, RN", "Halvorson, Eric, MD", "Hergrueter, Charles, MD", "Ingram, Abbie, PA-C", "Lafleur, Emily, PA-C", "Lahair, Tracy, PA-C" ],
        "DEPARTMENT" : [ "Plastic Surgery" ]
      },
      "currentFloor" : "3021ba43-9ef0-4d9e-a68d-7918bd77b9ed",
      "buildingDestinations" : [ "Carty, Matthew, MD", "Caterson, Stephanie, MD", "Chun, Yoon Sun, MD", "Hajj, Micheline, RN", "Halvorson, Eric, MD", "Hergrueter, Charles, MD", "Ingram, Abbie, PA-C", "Lafleur, Emily, PA-C", "Lahair, Tracy, PA-C", "Plastic Surgery" ]
    }, {
      "uniqueID" : "10fa7fcf-0ae3-4be7-9f44-a8414333eb4a",
      "heuristicCost" : 0.0,
      "location" : {
        "x" : 20.0,
        "y" : 40.0
      },
      "adjacentLocationNodes" : [ ],
      "destinations" : {
        "DEPARTMENT" : [ "Physical Therapy" ]
      },
      "currentFloor" : "3021ba43-9ef0-4d9e-a68d-7918bd77b9ed",
      "buildingDestinations" : [ "Physical Therapy" ]
    }, {
      "uniqueID" : "7562829b-58ba-48e1-939d-be1da16bd4aa",
      "heuristicCost" : 0.0,
      "location" : {
        "x" : 20.0,
        "y" : 50.0
      },
      "adjacentLocationNodes" : [ ],
      "destinations" : {
        "DEPARTMENT" : [ "Psychology" ]
      },
      "currentFloor" : "3021ba43-9ef0-4d9e-a68d-7918bd77b9ed",
      "buildingDestinations" : [ "Psychology" ]
    } ],
    "imagePath" : "Floor2_Draft.png"
  }, {
    "uniqueID" : "8deca8be-7a3e-4846-abea-5da320d70b0b",
    "floor" : 3,
    "currentBuilding" : "4dba3c24-3267-49ab-9d26-e42b24942b50",
    "locationNodes" : [ {
      "uniqueID" : "ad0780d0-6fa9-4cea-838b-fbe8eb79fe3c",
      "heuristicCost" : 0.0,
      "location" : {
        "x" : 30.0,
        "y" : 10.0
      },
      "adjacentLocationNodes" : [ ],
      "destinations" : {
        "PHYSICIAN" : [ "Byrne, Jennifer, RN, CPNP", "Grossi, Lisa, RN, MS, CPNP", "Keller, Elisabeth, MD", "Malone, Linda, DNP, RN, CPNP", "Morrison, Beverly, MD", "O'Connor, Elizabeth, MD", "Saluti, Andrew, DO", "Scheff, David, MD", "Stacks, Robert, MD", "Tunick, Mitchell, MD", "Viola, Julianne, MD" ],
        "DEPARTMENT" : [ "Roslindale Pediatric Associates" ]
      },
      "currentFloor" : "8deca8be-7a3e-4846-abea-5da320d70b0b",
      "buildingDestinations" : [ "Byrne, Jennifer, RN, CPNP", "Grossi, Lisa, RN, MS, CPNP", "Keller, Elisabeth, MD", "Malone, Linda, DNP, RN, CPNP", "Morrison, Beverly, MD", "O'Connor, Elizabeth, MD", "Saluti, Andrew, DO", "Scheff, David, MD", "Stacks, Robert, MD", "Tunick, Mitchell, MD", "Viola, Julianne, MD", "Roslindale Pediatric Associates" ]
    }, {
      "uniqueID" : "dc6650f0-0e10-4c01-8600-e84623acf896",
      "heuristicCost" : 0.0,
      "location" : {
        "x" : 30.0,
        "y" : 20.0
      },
      "adjacentLocationNodes" : [ ],
      "destinations" : {
        "PHYSICIAN" : [ "Dann, Harriet, MD", "Frangieh, George, MD", "Micley, Bruce, MD", "Patten, James, MD" ],
        "DEPARTMENT" : [ "Eye Care Specialists", "Suburban Eye Specialists" ]
      },
      "currentFloor" : "8deca8be-7a3e-4846-abea-5da320d70b0b",
      "buildingDestinations" : [ "Dann, Harriet, MD", "Frangieh, George, MD", "Micley, Bruce, MD", "Patten, James, MD", "Eye Care Specialists", "Suburban Eye Specialists" ]
    }, {
      "uniqueID" : "449ab91e-98dd-4274-a75f-1ad2a4b1b35a",
      "heuristicCost" : 0.0,
      "location" : {
        "x" : 30.0,
        "y" : 30.0
      },
      "adjacentLocationNodes" : [ ],
      "destinations" : {
        "PHYSICIAN" : [ "Greenberg, James Adam, MD", "Miner, Julie, MD", "Nadarajah, Sarah, WHNP", "Schueler, Leila, MD", "Smith, Shannon, MD" ],
        "DEPARTMENT" : [ "Obstetrics and Gynecology Associates" ]
      },
      "currentFloor" : "8deca8be-7a3e-4846-abea-5da320d70b0b",
      "buildingDestinations" : [ "Greenberg, James Adam, MD", "Miner, Julie, MD", "Nadarajah, Sarah, WHNP", "Schueler, Leila, MD", "Smith, Shannon, MD", "Obstetrics and Gynecology Associates" ]
    }, {
      "uniqueID" : "e4a7edef-e5b0-4773-8e82-2e1000f865a2",
      "heuristicCost" : 0.0,
      "location" : {
        "x" : 30.0,
        "y" : 40.0
      },
      "adjacentLocationNodes" : [ ],
      "destinations" : {
        "SERVICE" : [ "ATM" ]
      },
      "currentFloor" : "8deca8be-7a3e-4846-abea-5da320d70b0b",
      "buildingDestinations" : [ "ATM" ]
    }, {
      "uniqueID" : "f3a0ad08-e78d-49a6-9192-c2cf4ba3bae6",
      "heuristicCost" : 0.0,
      "location" : {
        "x" : 30.0,
        "y" : 50.0
      },
      "adjacentLocationNodes" : [ ],
      "destinations" : {
        "SERVICE" : [ "Huvos Auditorium" ]
      },
      "currentFloor" : "8deca8be-7a3e-4846-abea-5da320d70b0b",
      "buildingDestinations" : [ "Huvos Auditorium" ]
    }, {
      "uniqueID" : "ff756721-31f6-4ed7-9241-5addd92ff7d0",
      "heuristicCost" : 0.0,
      "location" : {
        "x" : 30.0,
        "y" : 60.0
      },
      "adjacentLocationNodes" : [ ],
      "destinations" : {
        "SERVICE" : [ "Cafeteria" ]
      },
      "currentFloor" : "8deca8be-7a3e-4846-abea-5da320d70b0b",
      "buildingDestinations" : [ "Cafeteria" ]
    }, {
      "uniqueID" : "33c53174-cbd7-4332-b2bb-015f3005ae92",
      "heuristicCost" : 0.0,
      "location" : {
        "x" : 30.0,
        "y" : 70.0
      },
      "adjacentLocationNodes" : [ ],
      "destinations" : {
        "SERVICE" : [ "Chapel" ]
      },
      "currentFloor" : "8deca8be-7a3e-4846-abea-5da320d70b0b",
      "buildingDestinations" : [ "Chapel" ]
    }, {
      "uniqueID" : "62511cb8-6147-48a5-a7d3-029ee950c6c4",
      "heuristicCost" : 0.0,
      "location" : {
        "x" : 30.0,
        "y" : 80.0
      },
      "adjacentLocationNodes" : [ ],
      "destinations" : {
        "SERVICE" : [ "Gift Shop" ]
      },
      "currentFloor" : "8deca8be-7a3e-4846-abea-5da320d70b0b",
      "buildingDestinations" : [ "Gift Shop" ]
    }, {
      "uniqueID" : "d5837699-6d97-4d9e-9958-9f83702f7ada",
      "heuristicCost" : 0.0,
      "location" : {
        "x" : 30.0,
        "y" : 90.0
      },
      "adjacentLocationNodes" : [ ],
      "destinations" : {
        "SERVICE" : [ "Patient Relations" ]
      },
      "currentFloor" : "8deca8be-7a3e-4846-abea-5da320d70b0b",
      "buildingDestinations" : [ "Patient Relations" ]
    }, {
      "uniqueID" : "a47d674d-5cb8-463f-a4e9-52cab35f62b8",
      "heuristicCost" : 0.0,
      "location" : {
        "x" : 30.0,
        "y" : 100.0
      },
      "adjacentLocationNodes" : [ ],
      "destinations" : {
        "SERVICE" : [ "Volunteer Services" ]
      },
      "currentFloor" : "8deca8be-7a3e-4846-abea-5da320d70b0b",
      "buildingDestinations" : [ "Volunteer Services" ]
    }, {
      "uniqueID" : "41596fd7-4d52-4ed1-ba88-3453510e31e2",
      "heuristicCost" : 0.0,
      "location" : {
        "x" : 30.0,
        "y" : 10.0
      },
      "adjacentLocationNodes" : [ ],
      "destinations" : {
        "PHYSICIAN" : [ "Byrne, Jennifer, RN, CPNP", "Grossi, Lisa, RN, MS, CPNP", "Keller, Elisabeth, MD", "Malone, Linda, DNP, RN, CPNP", "Morrison, Beverly, MD", "O'Connor, Elizabeth, MD", "Saluti, Andrew, DO", "Scheff, David, MD", "Stacks, Robert, MD", "Tunick, Mitchell, MD", "Viola, Julianne, MD" ],
        "DEPARTMENT" : [ "Roslindale Pediatric Associates" ]
      },
      "currentFloor" : "8deca8be-7a3e-4846-abea-5da320d70b0b",
      "buildingDestinations" : [ "Byrne, Jennifer, RN, CPNP", "Grossi, Lisa, RN, MS, CPNP", "Keller, Elisabeth, MD", "Malone, Linda, DNP, RN, CPNP", "Morrison, Beverly, MD", "O'Connor, Elizabeth, MD", "Saluti, Andrew, DO", "Scheff, David, MD", "Stacks, Robert, MD", "Tunick, Mitchell, MD", "Viola, Julianne, MD", "Roslindale Pediatric Associates" ]
    }, {
      "uniqueID" : "8444075b-b718-415e-9635-c3c4944d10dc",
      "heuristicCost" : 0.0,
      "location" : {
        "x" : 30.0,
        "y" : 20.0
      },
      "adjacentLocationNodes" : [ ],
      "destinations" : {
        "PHYSICIAN" : [ "Dann, Harriet, MD", "Frangieh, George, MD", "Micley, Bruce, MD", "Patten, James, MD" ],
        "DEPARTMENT" : [ "Eye Care Specialists", "Suburban Eye Specialists" ]
      },
      "currentFloor" : "8deca8be-7a3e-4846-abea-5da320d70b0b",
      "buildingDestinations" : [ "Dann, Harriet, MD", "Frangieh, George, MD", "Micley, Bruce, MD", "Patten, James, MD", "Eye Care Specialists", "Suburban Eye Specialists" ]
    }, {
      "uniqueID" : "2aaa576d-8c65-42c4-836b-607ea68bc3eb",
      "heuristicCost" : 0.0,
      "location" : {
        "x" : 30.0,
        "y" : 30.0
      },
      "adjacentLocationNodes" : [ ],
      "destinations" : {
        "PHYSICIAN" : [ "Greenberg, James Adam, MD", "Miner, Julie, MD", "Nadarajah, Sarah, WHNP", "Schueler, Leila, MD", "Smith, Shannon, MD" ],
        "DEPARTMENT" : [ "Obstetrics and Gynecology Associates" ]
      },
      "currentFloor" : "8deca8be-7a3e-4846-abea-5da320d70b0b",
      "buildingDestinations" : [ "Greenberg, James Adam, MD", "Miner, Julie, MD", "Nadarajah, Sarah, WHNP", "Schueler, Leila, MD", "Smith, Shannon, MD", "Obstetrics and Gynecology Associates" ]
    }, {
      "uniqueID" : "4500c99e-087b-432a-8530-05403e2a2d6b",
      "heuristicCost" : 0.0,
      "location" : {
        "x" : 30.0,
        "y" : 40.0
      },
      "adjacentLocationNodes" : [ ],
      "destinations" : {
        "SERVICE" : [ "ATM" ]
      },
      "currentFloor" : "8deca8be-7a3e-4846-abea-5da320d70b0b",
      "buildingDestinations" : [ "ATM" ]
    }, {
      "uniqueID" : "e33bd209-97c3-4956-9a50-564114aec961",
      "heuristicCost" : 0.0,
      "location" : {
        "x" : 30.0,
        "y" : 50.0
      },
      "adjacentLocationNodes" : [ ],
      "destinations" : {
        "SERVICE" : [ "Huvos Auditorium" ]
      },
      "currentFloor" : "8deca8be-7a3e-4846-abea-5da320d70b0b",
      "buildingDestinations" : [ "Huvos Auditorium" ]
    }, {
      "uniqueID" : "255c9e9b-4e23-414f-977d-a676d541e96b",
      "heuristicCost" : 0.0,
      "location" : {
        "x" : 30.0,
        "y" : 60.0
      },
      "adjacentLocationNodes" : [ ],
      "destinations" : {
        "SERVICE" : [ "Cafeteria" ]
      },
      "currentFloor" : "8deca8be-7a3e-4846-abea-5da320d70b0b",
      "buildingDestinations" : [ "Cafeteria" ]
    }, {
      "uniqueID" : "784e55c0-03a8-4d46-bd20-264293151236",
      "heuristicCost" : 0.0,
      "location" : {
        "x" : 30.0,
        "y" : 70.0
      },
      "adjacentLocationNodes" : [ ],
      "destinations" : {
        "SERVICE" : [ "Chapel" ]
      },
      "currentFloor" : "8deca8be-7a3e-4846-abea-5da320d70b0b",
      "buildingDestinations" : [ "Chapel" ]
    }, {
      "uniqueID" : "3dfddf87-20a8-4ed7-9960-43e32881732e",
      "heuristicCost" : 0.0,
      "location" : {
        "x" : 30.0,
        "y" : 80.0
      },
      "adjacentLocationNodes" : [ ],
      "destinations" : {
        "SERVICE" : [ "Gift Shop" ]
      },
      "currentFloor" : "8deca8be-7a3e-4846-abea-5da320d70b0b",
      "buildingDestinations" : [ "Gift Shop" ]
    }, {
      "uniqueID" : "05cbbd36-4150-4daa-a0b2-aeca79168928",
      "heuristicCost" : 0.0,
      "location" : {
        "x" : 30.0,
        "y" : 90.0
      },
      "adjacentLocationNodes" : [ ],
      "destinations" : {
        "SERVICE" : [ "Patient Relations" ]
      },
      "currentFloor" : "8deca8be-7a3e-4846-abea-5da320d70b0b",
      "buildingDestinations" : [ "Patient Relations" ]
    }, {
      "uniqueID" : "a45e9b6f-9227-4866-b738-eda4628d1d13",
      "heuristicCost" : 0.0,
      "location" : {
        "x" : 30.0,
        "y" : 100.0
      },
      "adjacentLocationNodes" : [ ],
      "destinations" : {
        "SERVICE" : [ "Volunteer Services" ]
      },
      "currentFloor" : "8deca8be-7a3e-4846-abea-5da320d70b0b",
      "buildingDestinations" : [ "Volunteer Services" ]
    } ],
    "imagePath" : "Floor3_Final.png"
  }, {
    "uniqueID" : "859a8cba-c489-4c58-8885-04ff98bea9e0",
    "floor" : 4,
    "currentBuilding" : "4dba3c24-3267-49ab-9d26-e42b24942b50",
    "locationNodes" : [ ],
    "imagePath" : "Floor4_Draft.png"
  } ],
  "destinations" : [ "Audiology", "Cardiac Rehabilitation", "Center for Preoperative Evaluation", "Emergency Room", "GI Endoscopy", "Laboratory", "Patient Financial Services", "Radiology", "Special Testing", "Taiclet Family Center", "Audiology", "Cardiac Rehabilitation", "Center for Preoperative Evaluation", "Emergency Room", "GI Endoscopy", "Laboratory", "Patient Financial Services", "Radiology", "Special Testing", "Taiclet Family Center", "Corrales, Carleton Eduardo, MD", "Prince, Anthony, MD", "Roditi, Rachel, MD", "Otolarngology", "Carty, Matthew, MD", "Caterson, Stephanie, MD", "Chun, Yoon Sun, MD", "Hajj, Micheline, RN", "Halvorson, Eric, MD", "Hergrueter, Charles, MD", "Ingram, Abbie, PA-C", "Lafleur, Emily, PA-C", "Lahair, Tracy, PA-C", "Plastic Surgery", "Physical Therapy", "Psychology", "Corrales, Carleton Eduardo, MD", "Prince, Anthony, MD", "Roditi, Rachel, MD", "Otolarngology", "Carty, Matthew, MD", "Caterson, Stephanie, MD", "Chun, Yoon Sun, MD", "Hajj, Micheline, RN", "Halvorson, Eric, MD", "Hergrueter, Charles, MD", "Ingram, Abbie, PA-C", "Lafleur, Emily, PA-C", "Lahair, Tracy, PA-C", "Plastic Surgery", "Physical Therapy", "Psychology", "Byrne, Jennifer, RN, CPNP", "Grossi, Lisa, RN, MS, CPNP", "Keller, Elisabeth, MD", "Malone, Linda, DNP, RN, CPNP", "Morrison, Beverly, MD", "O'Connor, Elizabeth, MD", "Saluti, Andrew, DO", "Scheff, David, MD", "Stacks, Robert, MD", "Tunick, Mitchell, MD", "Viola, Julianne, MD", "Roslindale Pediatric Associates", "Dann, Harriet, MD", "Frangieh, George, MD", "Micley, Bruce, MD", "Patten, James, MD", "Eye Care Specialists", "Suburban Eye Specialists", "Greenberg, James Adam, MD", "Miner, Julie, MD", "Nadarajah, Sarah, WHNP", "Schueler, Leila, MD", "Smith, Shannon, MD", "Obstetrics and Gynecology Associates", "ATM", "Huvos Auditorium", "Cafeteria", "Chapel", "Gift Shop", "Patient Relations", "Volunteer Services", "Byrne, Jennifer, RN, CPNP", "Grossi, Lisa, RN, MS, CPNP", "Keller, Elisabeth, MD", "Malone, Linda, DNP, RN, CPNP", "Morrison, Beverly, MD", "O'Connor, Elizabeth, MD", "Saluti, Andrew, DO", "Scheff, David, MD", "Stacks, Robert, MD", "Tunick, Mitchell, MD", "Viola, Julianne, MD", "Roslindale Pediatric Associates", "Dann, Harriet, MD", "Frangieh, George, MD", "Micley, Bruce, MD", "Patten, James, MD", "Eye Care Specialists", "Suburban Eye Specialists", "Greenberg, James Adam, MD", "Miner, Julie, MD", "Nadarajah, Sarah, WHNP", "Schueler, Leila, MD", "Smith, Shannon, MD", "Obstetrics and Gynecology Associates", "ATM", "Huvos Auditorium", "Cafeteria", "Chapel", "Gift Shop", "Patient Relations", "Volunteer Services" ]
}